memDataset/__init__.py
memDataset/_modidx.py
memDataset/core.py
memDataset-0.0.1.dist-info/LICENSE
memDataset-0.0.1.dist-info/METADATA
memDataset-0.0.1.dist-info/WHEEL
memDataset-0.0.1.dist-info/entry_points.txt
memDataset-0.0.1.dist-info/top_level.txt
memDataset-0.0.1.dist-info/RECORD
